nfer_image/cluster.py
nfer_image/embedding.py
nfer_image/hpa_utils.py
nfer_image-0.2.dist-info/METADATA
nfer_image-0.2.dist-info/WHEEL
nfer_image-0.2.dist-info/top_level.txt
nfer_image-0.2.dist-info/RECORD
