Metadata-Version: 2.1
Name: nfer-image
Version: 0.2
Summary: utilities for working with images
Home-page: UNKNOWN
Author: Martin Kang
Author-email: martin@nference.net
License: UNKNOWN
Platform: UNKNOWN
Requires-Dist: matplotlib
Requires-Dist: numpy
Requires-Dist: opencv-python
Requires-Dist: boto3
Requires-Dist: tqdm
Requires-Dist: pathlib
Requires-Dist: scikit-image
Requires-Dist: sklearn
Requires-Dist: pandas
Requires-Dist: tensorflow
